linux_command/__init__.py
linux_command/linux_command.py
linux_command-0.2.3.dist-info/LICENSE
linux_command-0.2.3.dist-info/METADATA
linux_command-0.2.3.dist-info/WHEEL
linux_command-0.2.3.dist-info/entry_points.txt
linux_command-0.2.3.dist-info/top_level.txt
linux_command-0.2.3.dist-info/RECORD
