Metadata-Version: 2.1
Name: linux-command
Version: 0.2.3
Summary: A command line tool to perform custom tasks.
Home-page: https://github.com/MouxiaoHuang/linux-command
Author: Mouxiao Huang
Author-email: huangmouxiao@gmail.com
Classifier: Programming Language :: Python :: 3
Classifier: License :: OSI Approved :: MIT License
Classifier: Operating System :: OS Independent
Requires-Python: >=3.6
License-File: LICENSE
